LICENSE
MANIFEST.in
README.rst
setup.cfg
setup.py
pypack/pypack_cli/__init__.py
pypack_cli.egg-info/PKG-INFO
pypack_cli.egg-info/SOURCES.txt
pypack_cli.egg-info/dependency_links.txt
pypack_cli.egg-info/entry_points.txt
pypack_cli.egg-info/top_level.txt