Metadata-Version: 1.2
Name: pypack-cli
Version: 0.0.1
Summary: pypack cli interface
Home-page: http://github.com/pypack/pypack-cli
Author: Giovanni Cardamone (MrStep)
Author-email: g.cardamone2@gmail.com
License: MIT
Keywords: pypack
Platform: UNKNOWN
Requires-Python: >=3
